analytics_service/__init__.py
analytics_service/api.py
analytics_service/crawler.py
analytics_service/embeddings.py
analytics_service/server.py
mseep_analytics_service-0.1.1.dist-info/METADATA
mseep_analytics_service-0.1.1.dist-info/WHEEL
mseep_analytics_service-0.1.1.dist-info/entry_points.txt
mseep_analytics_service-0.1.1.dist-info/licenses/LICENSE
mseep_analytics_service-0.1.1.dist-info/RECORD
