Metadata-Version: 2.4
Name: mseep-analytics-service
Version: 0.1.1
Summary: A MCP server for website tracking data
Author-email: mseep <support@skydeck.ai>
License-File: LICENSE
Requires-Python: >=3.12
Requires-Dist: crawl4ai>=0.3.0
Requires-Dist: faiss-cpu>=1.7.4
Requires-Dist: httpx>=0.28.0
Requires-Dist: langchain-community>=0.0.21
Requires-Dist: langchain-openai>=0.0.5
Requires-Dist: langchain>=0.1.9
Requires-Dist: mcp>=1.0.0
Requires-Dist: numpy>=1.26.0
Requires-Dist: openai>=1.12.0
Requires-Dist: pillow>=9.4.0
Requires-Dist: python-dotenv>=1.0.1
Requires-Dist: requests>=2.31.0
Requires-Dist: scikit-learn>=1.4.0
Requires-Dist: sentence-transformers>=2.5.1
